{"resourceType":"StructureDefinition","id":"7a8fe1be-015a-46b9-9f86-92ee25a014f9","url":"https://fhir.nhs.uk/StructureDefinition/Extension-EPS-TaskBusinessStatusReason","name":"ExtensionEPSTaskBusinessStatusReason","status":"draft","fhirVersion":"4.0.1","kind":"complex-type","abstract":false,"context":[{"type":"element","expression":"Claim.item"},{"type":"element","expression":"Claim.item.detail"}],"type":"Extension","baseDefinition":"http://hl7.org/fhir/StructureDefinition/Extension","derivation":"constraint","differential":{"element":[{"id":"Extension.url","path":"Extension.url","fixedUri":"https://fhir.nhs.uk/StructureDefinition/Extension-EPS-TaskBusinessStatusReason"},{"id":"Extension.value[x]","path":"Extension.value[x]","min":1,"type":[{"code":"Coding"}]},{"id":"Extension.value[x].system","path":"Extension.value[x].system","min":1},{"id":"Extension.value[x].code","path":"Extension.value[x].code","min":1}]}}