{"resourceType":"StructureDefinition","url":"https://fhir.nhs.uk/StructureDefinition/Extension-NHSDigital-CapabilityStatement-Package","name":"ExtensionCapabilityStatementPackage","status":"draft","fhirVersion":"4.0.1","mapping":[{"identity":"rim","uri":"http://hl7.org/v3","name":"RIM Mapping"}],"kind":"complex-type","abstract":false,"context":[{"type":"element","expression":"CapabilityStatement"}],"type":"Extension","baseDefinition":"http://hl7.org/fhir/StructureDefinition/Extension","derivation":"constraint","differential":{"element":[{"id":"Extension.extension","path":"Extension.extension","slicing":{"discriminator":[{"type":"value","path":"url"}],"rules":"open"}},{"id":"Extension.extension:openApi","path":"Extension.extension","sliceName":"openApi"},{"id":"Extension.extension:openApi.extension","path":"Extension.extension.extension","slicing":{"discriminator":[{"type":"value","path":"url"}],"rules":"open"}},{"id":"Extension.extension:openApi.extension:documentation","path":"Extension.extension.extension","sliceName":"documentation","min":1,"max":"1"},{"id":"Extension.extension:openApi.extension:documentation.url","path":"Extension.extension.extension.url","fixedUri":"documentation"},{"id":"Extension.extension:openApi.extension:documentation.value[x]","path":"Extension.extension.extension.value[x]","min":1,"type":[{"code":"url"}]},{"id":"Extension.extension:openApi.extension:description","path":"Extension.extension.extension","sliceName":"description","max":"1"},{"id":"Extension.extension:openApi.extension:description.url","path":"Extension.extension.extension.url","fixedUri":"description"},{"id":"Extension.extension:openApi.extension:description.value[x]","path":"Extension.extension.extension.value[x]","min":1,"type":[{"code":"string"}]},{"id":"Extension.extension:openApi.url","path":"Extension.extension.url","fixedUri":"openApi"},{"id":"Extension.extension:openApi.value[x]","path":"Extension.extension.value[x]","max":"0"},{"id":"Extension.extension:FHIRPackage","path":"Extension.extension","sliceName":"FHIRPackage","min":1},{"id":"Extension.extension:FHIRPackage.extension","path":"Extension.extension.extension","slicing":{"discriminator":[{"type":"value","path":"url"}],"rules":"open"}},{"id":"Extension.extension:FHIRPackage.extension:name","path":"Extension.extension.extension","sliceName":"name","min":1,"max":"1"},{"id":"Extension.extension:FHIRPackage.extension:name.url","path":"Extension.extension.extension.url","fixedUri":"name"},{"id":"Extension.extension:FHIRPackage.extension:name.value[x]","path":"Extension.extension.extension.value[x]","min":1,"type":[{"code":"string"}]},{"id":"Extension.extension:FHIRPackage.extension:version","path":"Extension.extension.extension","sliceName":"version","max":"1"},{"id":"Extension.extension:FHIRPackage.extension:version.url","path":"Extension.extension.extension.url","fixedUri":"version"},{"id":"Extension.extension:FHIRPackage.extension:version.value[x]","path":"Extension.extension.extension.value[x]"},{"id":"Extension.extension:FHIRPackage.url","path":"Extension.extension.url","fixedUri":"FHIRPackage"},{"id":"Extension.extension:FHIRPackage.value[x]","path":"Extension.extension.value[x]","max":"0"},{"id":"Extension.url","path":"Extension.url","fixedUri":"https://fhir.nhs.uk/StructureDefinition/Extension-NHSDigital-CapabilityStatement-Package"},{"id":"Extension.value[x]","path":"Extension.value[x]","max":"0"}]}}